Metadata-Version: 1.1
Name: facepy
Version: 0.9.0
Summary: Facepy makes it really easy to interact with Facebook's Graph API
Home-page: http://github.com/jgorset/facepy
Author: Johannes Gorset
Author-email: jgorset@gmail.com
License: UNKNOWN
Platform: UNKNOWN
Classifier: Development Status :: 5 - Production/Stable
Classifier: Intended Audience :: Developers
Classifier: Natural Language :: English
Classifier: License :: OSI Approved :: MIT License
Classifier: Programming Language :: Python
Classifier: Programming Language :: Python :: 2.6
Classifier: Programming Language :: Python :: 2.7
